Workbook

Sheet Raw Data
A1: 📊 SALES RAW DATA — 2024
A3: Order ID | B3: Month | C3: Region | D3: Salesperson | E3: Product | F3: Category | G3: Units Sold | H3: Unit Price ($) | I3: Revenue ($) | J3: Cost ($) | K3: Profit ($) | L3: Profit Margin (%)
A4: ORD-1001 | B4: Jan | C4: North | D4: Alice M. | E4: Chair | F4: Furniture | G4: 9 | H4: 150 | I4: 1350 | J4: 810 | K4: 540 | L4: =K4/I4 -> 0.4
A5: ORD-1002 | B5: Feb | C5: South | D5: Cara S. | E5: Phone | F5: Electronics | G5: 23 | H5: 400 | I5: 9200 | J5: 5750 | K5: 3450 | L5: =K5/I5 -> 0.375
A6: ORD-1003 | B6: Mar | C6: North | D6: Gail P. | E6: Laptop | F6: Electronics | G6: 2 | H6: 800 | I6: 1600 | J6: 1000 | K6: 600 | L6: =K6/I6 -> 0.375
A7: ORD-1004 | B7: Apr | C7: North | D7: Dan T. | E7: Desk | F7: Furniture | G7: 18 | H7: 200 | I7: 3600 | J7: 2160 | K7: 1440 | L7: =K7/I7 -> 0.4
A8: ORD-1005 | B8: May | C8: North | D8: Dan T. | E8: Lamp | F8: Furniture | G8: 15 | H8: 60 | I8: 900 | J8: 525 | K8: 375 | L8: =K8/I8 -> 0.41666667
A9: ORD-1006 | B9: Jun | C9: South | D9: Hiro W. | E9: Notebook | F9: Stationery | G9: 10 | H9: 15 | I9: 150 | J9: 50 | K9: 100 | L9: =K9/I9 -> 0.66666667
A10: ORD-1007 | B10: Jul | C10: North | D10: Cara S. | E10: Headset | F10: Electronics | G10: 12 | H10: 80 | I10: 960 | J10: 540 | K10: 420 | L10: =K10/I10 -> 0.4375
A11: ORD-1008 | B11: Aug | C11: East | D11: Cara S. | E11: Desk | F11: Furniture | G11: 12 | H11: 200 | I11: 2400 | J11: 1440 | K11: 960 | L11: =K11/I11 -> 0.4
A12: ORD-1009 | B12: Sep | C12: North | D12: Bob K. | E12: Headset | F12: Electronics | G12: 5 | H12: 80 | I12: 400 | J12: 225 | K12: 175 | L12: =K12/I12 -> 0.4375
A13: ORD-1010 | B13: Oct | C13: East | D13: Finn O. | E13: Notebook | F13: Stationery | G13: 10 | H13: 15 | I13: 150 | J13: 50 | K13: 100 | L13: =K13/I13 -> 0.66666667
A14: ORD-1011 | B14: Nov | C14: North | D14: Hiro W. | E14: Lamp | F14: Furniture | G14: 5 | H14: 60 | I14: 300 | J14: 175 | K14: 125 | L14: =K14/I14 -> 0.41666667
A15: ORD-1012 | B15: Dec | C15: West | D15: Bob K. | E15: Lamp | F15: Furniture | G15: 11 | H15: 60 | I15: 660 | J15: 385 | K15: 275 | L15: =K15/I15 -> 0.41666667
... A123: ORD-1120 | B123: Dec | C123: South | D123: Gail P. | E123: Keyboard | F123: Electronics | G123: 14 | H123: 50 | I123: 700 | J123: 392 | K123: 308 | L123: =K123/I123 -> 0.44

Sheet Sales Dashboard
A1: 📊 SALES PERFORMANCE DASHBOARD 2024
A2: Interactive KPI Overview | Revenue · Profit · Regional Performance · Product Analysis
A4: 💰 Total Revenue | D4: 📈 Total Profit | G4: 📦 Total Orders | J4: 🎯 Avg Margin
A5: =SUMIF('Raw Data'!I4:I123,">0",'Raw Data'!I4:I123) -> 294100 | D5: =SUMIF('Raw Data'!K4:K123,">0",'Raw Data'!K4:K123) -> 115610 | G5: =COUNTA('Raw Data'!A4:A123) -> 120 | J5: =AVERAGE('Raw Data'!L4:L123) -> 0.42754861
A9: Monthly Revenue Breakdown | H9: Revenue by Region
A10: Month | B10: Total Revenue | C10: Total Profit | D10: Orders | E10: Avg Order Value | F10: Growth % | H10: Region | I10: Revenue | J10: Profit | K10: Orders | L10: Share %
A11: Jan | B11: =SUMIF('Raw Data'!B4:B123,A11,'Raw Data'!I4:I123) -> 16810 | C11: =SUMIF('Raw Data'!B4:B123,A11,'Raw Data'!K4:K123) -> 6789 | D11: =COUNTIF('Raw Data'!B4:B123,A11) -> 10 | E11: =IF(D11>0,B11/D11,0) -> 1681 | F11: — | H11: North | I11: =SUMIF('Raw Data'!C4:C123,H11,'Raw Data'!I4:I123) -> 61855 | J11: =SUMIF('Raw Data'!C4:C123,H11,'Raw Data'!K4:K123) -> 24601 | K11: =COUNTIF('Raw Data'!C4:C123,H11) -> 35 | L11: =IF(SUM(I11:I14)>0,I11/SUM(I$11:I$14),0) -> 0.21031962
A12: Feb | B12: =SUMIF('Raw Data'!B4:B123,A12,'Raw Data'!I4:I123) -> 27020 | C12: =SUMIF('Raw Data'!B4:B123,A12,'Raw Data'!K4:K123) -> 10695 | D12: =COUNTIF('Raw Data'!B4:B123,A12) -> 10 | E12: =IF(D12>0,B12/D12,0) -> 2702 | F12: =IF(B11>0,(B12-B11)/B11,0) -> 0.60737656 | H12: South | I12: =SUMIF('Raw Data'!C4:C123,H12,'Raw Data'!I4:I123) -> 82070 | J12: =SUMIF('Raw Data'!C4:C123,H12,'Raw Data'!K4:K123) -> 32410 | K12: =COUNTIF('Raw Data'!C4:C123,H12) -> 30 | L12: =IF(SUM(I11:I14)>0,I12/SUM(I$11:I$14),0) -> 0.27905474
A13: Mar | B13: =SUMIF('Raw Data'!B4:B123,A13,'Raw Data'!I4:I123) -> 25100 | C13: =SUMIF('Raw Data'!B4:B123,A13,'Raw Data'!K4:K123) -> 9757 | D13: =COUNTIF('Raw Data'!B4:B123,A13) -> 10 | E13: =IF(D13>0,B13/D13,0) -> 2510 | F13: =IF(B12>0,(B13-B12)/B12,0) -> -0.071058475 | H13: East | I13: =SUMIF('Raw Data'!C4:C123,H13,'Raw Data'!I4:I123) -> 94595 | J13: =SUMIF('Raw Data'!C4:C123,H13,'Raw Data'!K4:K123) -> 37028 | K13: =COUNTIF('Raw Data'!C4:C123,H13) -> 31 | L13: =IF(SUM(I11:I14)>0,I13/SUM(I$11:I$14),0) -> 0.3216423
A14: Apr | B14: =SUMIF('Raw Data'!B4:B123,A14,'Raw Data'!I4:I123) -> 25080 | C14: =SUMIF('Raw Data'!B4:B123,A14,'Raw Data'!K4:K123) -> 9983 | D14: =COUNTIF('Raw Data'!B4:B123,A14) -> 10 | E14: =IF(D14>0,B14/D14,0) -> 2508 | F14: =IF(B13>0,(B14-B13)/B13,0) -> -0.00079681275 | H14: West | I14: =SUMIF('Raw Data'!C4:C123,H14,'Raw Data'!I4:I123) -> 55580 | J14: =SUMIF('Raw Data'!C4:C123,H14,'Raw Data'!K4:K123) -> 21571 | K14: =COUNTIF('Raw Data'!C4:C123,H14) -> 24 | L14: =IF(SUM(I11:I14)>0,I14/SUM(I$11:I$14),0) -> 0.18898334
A15: May | B15: =SUMIF('Raw Data'!B4:B123,A15,'Raw Data'!I4:I123) -> 32340 | C15: =SUMIF('Raw Data'!B4:B123,A15,'Raw Data'!K4:K123) -> 12542 | D15: =COUNTIF('Raw Data'!B4:B123,A15) -> 10 | E15: =IF(D15>0,B15/D15,0) -> 3234 | F15: =IF(B14>0,(B15-B14)/B14,0) -> 0.28947368
A16: Jun | B16: =SUMIF('Raw Data'!B4:B123,A16,'Raw Data'!I4:I123) -> 22145 | C16: =SUMIF('Raw Data'!B4:B123,A16,'Raw Data'!K4:K123) -> 8740 | D16: =COUNTIF('Raw Data'!B4:B123,A16) -> 10 | E16: =IF(D16>0,B16/D16,0) -> 2214.5 | F16: =IF(B15>0,(B16-B15)/B15,0) -> -0.31524428
A17: Jul | B17: =SUMIF('Raw Data'!B4:B123,A17,'Raw Data'!I4:I123) -> 34570 | C17: =SUMIF('Raw Data'!B4:B123,A17,'Raw Data'!K4:K123) -> 13365 | D17: =COUNTIF('Raw Data'!B4:B123,A17) -> 10 | E17: =IF(D17>0,B17/D17,0) -> 3457 | F17: =IF(B16>0,(B17-B16)/B16,0) -> 0.56107473
A18: Aug | B18: =SUMIF('Raw Data'!B4:B123,A18,'Raw Data'!I4:I123) -> 34240 | C18: =SUMIF('Raw Data'!B4:B123,A18,'Raw Data'!K4:K123) -> 13300 | D18: =COUNTIF('Raw Data'!B4:B123,A18) -> 10 | E18: =IF(D18>0,B18/D18,0) -> 3424 | F18: =IF(B17>0,(B18-B17)/B17,0) -> -0.009545849
A19: Sep | B19: =SUMIF('Raw Data'!B4:B123,A19,'Raw Data'!I4:I123) -> 15730 | C19: =SUMIF('Raw Data'!B4:B123,A19,'Raw Data'!K4:K123) -> 6195 | D19: =COUNTIF('Raw Data'!B4:B123,A19) -> 10 | E19: =IF(D19>0,B19/D19,0) -> 1573 | F19: =IF(B18>0,(B19-B18)/B18,0) -> -0.54059579
A20: Oct | B20: =SUMIF('Raw Data'!B4:B123,A20,'Raw Data'!I4:I123) -> 22875 | C20: =SUMIF('Raw Data'!B4:B123,A20,'Raw Data'!K4:K123) -> 9155 | D20: =COUNTIF('Raw Data'!B4:B123,A20) -> 10 | E20: =IF(D20>0,B20/D20,0) -> 2287.5 | F20: =IF(B19>0,(B20-B19)/B19,0) -> 0.45422759
A21: Nov | B21: =SUMIF('Raw Data'!B4:B123,A21,'Raw Data'!I4:I123) -> 19320 | C21: =SUMIF('Raw Data'!B4:B123,A21,'Raw Data'!K4:K123) -> 7492 | D21: =COUNTIF('Raw Data'!B4:B123,A21) -> 10 | E21: =IF(D21>0,B21/D21,0) -> 1932 | F21: =IF(B20>0,(B21-B20)/B20,0) -> -0.15540984
A22: Dec | B22: =SUMIF('Raw Data'!B4:B123,A22,'Raw Data'!I4:I123) -> 18870 | C22: =SUMIF('Raw Data'!B4:B123,A22,'Raw Data'!K4:K123) -> 7597 | D22: =COUNTIF('Raw Data'!B4:B123,A22) -> 10 | E22: =IF(D22>0,B22/D22,0) -> 1887 | F22: =IF(B21>0,(B22-B21)/B21,0) -> -0.023291925
A23: TOTAL | B23: =SUM(B11:B22) -> 294100 | C23: =SUM(C11:C22) -> 115610 | D23: =SUM(D11:D22) -> 120 | E23: =AVERAGE(E11:E22) -> 2450.8333
